pytgm/__init__.py
pytgm/b64.py
pytgm/file.py
pytgm/local_server.py
pytgm/sound.py
pytgm/graphics/__init__.py
pytgm/graphics/cls.py
pytgm/graphics/color.py
pytgm/graphics/pos.py
pytgm/terd/__init__.py
pytgm/terd/click.cp313-win_amd64.pyd
pytgm/terd/geky.py
pyTGM-4.0.6.dist-info/LICENCE.md
pyTGM-4.0.6.dist-info/METADATA
pyTGM-4.0.6.dist-info/WHEEL
pyTGM-4.0.6.dist-info/top_level.txt
pyTGM-4.0.6.dist-info/RECORD
