Metadata-Version: 2.1
Name: pyTGM
Version: 4.0.6
Summary: Terminal Game Maker
Home-page: https://youtube.tokynblast.space/programming/libraries/pytgm/init
Author: Tokyn Blast
Author-email: tokynblast@gmail.com
Maintainer: Tokyn Blast
Maintainer-email: tokynblast@gmail.com
License: Bspace
Keywords: game,game maker,terminal,tools,pytgm,terimnal input
Platform: Windows
Platform: Linux
Platform: MacOS
Classifier: Development Status :: 5 - Production/Stable
Classifier: Intended Audience :: Developers
Classifier: Operating System :: Microsoft :: Windows
Classifier: Operating System :: POSIX :: Linux
Classifier: Operating System :: MacOS
Classifier: License :: Other/Proprietary License
Classifier: Programming Language :: Python :: 3
Classifier: Programming Language :: Python :: 3.13
Requires-Python: >=3.13
License-File: LICENCE.md
